admincharts/__init__.py
admincharts/admin.py
admincharts/apps.py
admincharts/migrations/__init__.py
admincharts/models.py
admincharts/static/admincharts/admincharts.css
admincharts/static/admincharts/admincharts.js
admincharts/static/admincharts/chart.min.js
admincharts/templates/admin/admincharts/generic_change_list.html
admincharts/utils.py
django_admincharts-0.4.0.dist-info/LICENSE
django_admincharts-0.4.0.dist-info/WHEEL
django_admincharts-0.4.0.dist-info/METADATA
django_admincharts-0.4.0.dist-info/RECORD
