Metadata-Version: 2.1
Name: django-admincharts
Version: 0.4.0
Summary: Chart.js integration for Django admin models
Home-page: https://github.com/dropseed/django-admincharts
License: MIT
Keywords: Chart.js,django,admin,charts,graphs
Author: Dave Gaeddert
Author-email: dave.gaeddert@dropseed.dev
Requires-Python: >=3.8,<4.0
Classifier: Environment :: Web Environment
Classifier: Framework :: Django
Classifier: Framework :: Django :: 3
Classifier: Framework :: Django :: 4
Classifier: Intended Audience :: Developers
Classifier: License :: OSI Approved :: MIT License
Classifier: Operating System :: OS Independent
Classifier: Programming Language :: Python
Classifier: Programming Language :: Python :: 3
Classifier: Programming Language :: Python :: 3 :: Only
Classifier: Programming Language :: Python :: 3.10
Classifier: Programming Language :: Python :: 3.8
Classifier: Programming Language :: Python :: 3.9
Project-URL: Documentation, https://github.com/dropseed/django-admincharts
Project-URL: Repository, https://github.com/dropseed/django-admincharts
